{"ModuleTitle": "Company Description", "CompanyName": "Bassett Furniture Industries, Incorporated", "Symbol": "BSET", "Address": "PO BOX 626, BASSETT, Virginia, 24055, United States of America", "Phone": "5406296209", "Industry": "Home Furnishings", "Sector": "Consumer Durables", "Region": "North America", "CompanyDescription": "Bassett is a leading retailer, manufacturer and marketer of branded home\r\nfurnishings. Our products are sold primarily through a network of Company-owned\r\nand licensee-owned branded stores under the Bassett Home Furnishings\r\n(\"BHF\") name, with additional distribution through other wholesale channels\r\nincluding multi-line furniture stores, many of which feature Bassett galleries\r\nor design centers. We were founded in 1902 and incorporated under the laws of\r\nVirginia in 1930. Our rich 117-year history has instilled the principles of\r\nquality, value, and integrity in everything we do, while simultaneously\r\nproviding us with the expertise to respond to ever-changing consumer tastes and\r\nmeet the demands of a global economy.\r\n\r\n \r\n\r\nWith 103 BHF stores at November 30, 2019, we have leveraged our strong brand\r\nname in furniture into a network of Company-owned and licensed stores that focus\r\non providing consumers with a friendly environment for buying furniture and\r\naccessories.&nbsp;&nbsp;... <a href=\"http://secfilings.nasdaq.com/edgar_conv_html%2f2020%2f01%2f23%2f0001437749-20-001052.html#FIS_BUSINESS\" target=\"_blank\">More</a> ...&nbsp;&nbsp;\r\n", "KeyExecutives": [{"name": "John E. Bassett", "title": "Chief Operating Officer & Senior Vice President"}, {"name": "John Michael Daniel", "title": "SVP, Chief Financial & Administrative Officer"}, {"name": "Robert H. Spilman", "title": "Chairman, President & Chief Executive Officer"}, {"name": "Stephen D. Harmon", "title": "Vice President-Information Technology"}], "Number_of_employees": ["2,618"], "Subsidiaries": ["NO INFO"]}