{"Exchange": "NASDAQ-GS", "Sector": "Technology", "Industry": "Computer Software: Prepackaged Software", "OneYrTarget": "$332.00", "TodayHighLow": "$398.10/$385.84", "ShareVolume": "2,590,199", "AverageVolume": "3,171,098", "PreviousClose": "$392.90", "FiftTwoWeekHighLow": "$398.10/$255.13", "MarketCap": "191,650,742,113", "PERatio": 60.27, "ForwardPE1Yr": "49.72", "EarningsPerShare": "$6.60", "AnnualizedDividend": "N/A", "ExDividendDate": "N/A", "DividendPaymentDate": "N/A", "Yield": "N/A", "Beta": 1.0}