{"Exchange": "NASDAQ-GS", "Sector": "Finance", "Industry": "Banks", "OneYrTarget": "$22.00", "TodayHighLow": "$19.03/$17.79", "ShareVolume": "215,889", "AverageVolume": "203,961", "PreviousClose": "$18.10", "FiftTwoWeekHighLow": "$30.15/$14.65", "MarketCap": "682,240,271", "PERatio": 11.12, "ForwardPE1Yr": "13.58", "EarningsPerShare": "$1.71", "AnnualizedDividend": "$0.80", "ExDividendDate": "May 12, 2020", "DividendPaymentDate": "May 27, 2020", "Yield": "4.42%", "Beta": 1.0, "SpecialDividendDate": "Nov 6, 2019", "SpecialDividendAmount": "$0.10", "SpecialDividendPaymentDate": "Nov 21, 2019"}