{"Exchange": "NASDAQ-GS", "Sector": "Consumer Services", "Industry": "Office Equipment/Supplies/Services", "OneYrTarget": "$42.00", "TodayHighLow": "$33.87/$32.66", "ShareVolume": "1,258,454", "AverageVolume": "1,366,012", "PreviousClose": "$33.30", "FiftTwoWeekHighLow": "$43.25/$21.69", "MarketCap": "5,481,862,950", "PERatio": 13.43, "ForwardPE1Yr": "13.43", "EarningsPerShare": "$2.52", "AnnualizedDividend": "N/A", "ExDividendDate": "N/A", "DividendPaymentDate": "N/A", "Yield": "N/A", "Beta": 1.0}