{"ModuleTitle": "Company Description", "CompanyName": "BioMarin Pharmaceutical Inc.", "Symbol": "BMRN", "Address": "105 DIGITAL DRIVE, NOVATO, California, 94949, United States of America", "Phone": "4155066700", "Industry": "Major Pharmaceuticals", "Sector": "Health Care", "Region": "North America", "CompanyDescription": "BioMarin Pharmaceutical Inc. (BioMarin, we, us or our) is a global biotechnology\r\ncompany that develops and commercializes innovative therapies for people with\r\nserious and life-threatening rare diseases and medical conditions. We select\r\nproduct candidates for diseases and conditions that represent a significant\r\nunmet medical need, have well-understood biology and provide an opportunity to\r\nbe first-to-market or offer a significant benefit over existing products.\r\nOur portfolio consists of several commercial products and multiple clinical and\r\npreclinical product candidates for the treatment of various diseases. We\r\ncontinue to invest in our clinical and preclinical product pipeline by\r\ncommitting significant resources to research and development programs and\r\nbusiness development opportunities within our areas of scientific, manufacturing\r\nand technical expertise.&nbsp;&nbsp;... <a href=\"http://secfilings.nasdaq.com/edgar_conv_html%2f2020%2f02%2f27%2f0001048477-20-000009.html#FIS_BUSINESS\" target=\"_blank\">More</a> ...&nbsp;&nbsp;\r\n", "KeyExecutives": [{"name": "Brian R. Mueller", "title": "Chief Financial & Accounting Officer"}, {"name": "C. Greg Guyer", "title": "Chief Technical Officer"}, {"name": "Eduardo E. Von Pervieux", "title": "Chief Information Officer"}, {"name": "Geoffrey M. Nichol", "title": "Chief Medical Officer & Senior Vice President"}, {"name": "Henry J. Fuchs", "title": "President-Worldwide Research & Development"}, {"name": "Jean-Jacques BienaimT", "title": "Chairman & Chief Executive Officer"}, {"name": "Lon Cardon", "title": "Chief Scientific Strategy Officer"}, {"name": "Steve Maricich", "title": "Medical Director-Clinical Sciences"}], "Number_of_employees": ["2,581"], "Subsidiaries": ["NO INFO"]}