[{"SharesOutstandingPCT": ["36.22 %"], "ShareoutstandingTotal": ["18"], "TotalHoldingsValue": ["$32"]}, {"ActivePositions": ["Increased Positions", "Decreased Positions", "Held Positions", "Total Institutional Shares", "New Positions", "Sold Out Positions"], "Holders": ["16", "11", "7", "34", "4", "6"], "Shares": ["764,116", "216,965", "5,421,480", "6,402,561", "4,741", "70,478"]}, {"OWNER_NAME": ["BLEICHROEDER LP", "ROYCE & ASSOCIATES LP", "VANGUARD GROUP INC", "HEARTLAND ADVISORS INC", "ESSEX INVESTMENT MANAGEMENT CO LLC"], "DATE": ["03/31/2020", "03/31/2020", "03/31/2020", "03/31/2020", "03/31/2020"], "SHARES_HELD": ["2,196,389", "740,964", "694,300", "600,000", "472,104"], "CHANGE(Shares)": ["308,385", "-3,077", "147,856", "213,959", "-90,515"], "CHANGE(%)": ["16.334%", "-0.414%", "27.058%", "55.424%", "-16.088%"], "MARKET_VALUE": ["$10,938", "$3,690", "$3,458", "$2,988", "$2,351"]}]