{"ModuleTitle": "Company Description", "CompanyName": "Criteo S.A.", "Symbol": "CRTO", "Address": "32 RUE BLANCHE, PARIS, 75009, France", "Phone": "33140402290", "Industry": "Advertising", "Sector": "Technology", "Region": "Europe", "CompanyDescription": "Criteo S.A. was initially incorporated as a soci\u00e9t\u00e9 par actions simplifi\u00e9e, or\r\nS.A.S., under the laws of the French Republic on November 3, 2005, for a period\r\nof 99 years and subsequently converted to a soci\u00e9t\u00e9 anonyme, or S.A. We are\r\nregistered at the Paris Commerce and Companies Register under the number 484 786\r\n249. Our agent for service of process in the United States is National\r\nRegistered Agents, Inc. We began selling elements of our offering in France in\r\n2007 and have since expanded our business into other countries in Western\r\nEurope. In 2009, we expanded our business into North America and entered the\r\nAsia-Pacific region in late 2010. In 2016, we acquired HookLogic, Inc.\r\n(\"HookLogic\"), a New York-based company operating a performance marketing\r\nexchange connecting consumer brands with retail ecommerce sites via sponsored\r\nproduct ads.\r\nBusiness Overview\r\nWe are a global technology company powering the world's marketers with trusted\r\nand impactful advertising.&nbsp;&nbsp;... <a href=\"http://secfilings.nasdaq.com/edgar_conv_html%2f2020%2f03%2f02%2f0001576427-20-000011.html#FIS_BUSINESS\" target=\"_blank\">More</a> ...&nbsp;&nbsp;\r\n", "KeyExecutives": [{"name": "David John Anderson", "title": "Chief Financial & Accounting Officer"}, {"name": "Diarmuid Gill", "title": "Chief Technology Officer"}, {"name": "Megan Clarken", "title": "Chief Executive Officer"}], "Number_of_employees": [], "Subsidiaries": ["NO INFO"]}