{"ModuleTitle": "Company Description", "CompanyName": "Flexsteel Industries, Inc.", "Symbol": "FLXS", "Address": "385 BELL ST., DUBUQUE, Iowa, 52001, United States of America", "Phone": "3195567730", "Industry": "Home Furnishings", "Sector": "Consumer Durables", "Region": "North America", "CompanyDescription": "Flexsteel Industries, Inc. and Subsidiaries (the \"Company\") incorporated in 1929\r\ncelebrated its 125th anniversary of the Company's founding in 1893 during 2018. \r\nFlexsteel Industries, Inc. is one of the oldest and largest manufacturers,\r\nimporters and marketers of residential and contract upholstered and wooden\r\nfurniture products in the United States. Over the generations the Company has\r\nbuilt a committed retail and consumer following based on its patented,\r\nguaranteed-for-life Blue Steel SpringTM - the all-riveted, high-carbon,\r\nsteel-banded seating platform that gives upholstered and leather furniture the\r\nstrength and comfort to last a lifetime. With offerings for use in home,\r\nhealthcare, and recreational seating, the Company distributes its furniture\r\nthroughout the United States and Canada through the Company's sales force and\r\nvarious independent representatives.\r\n\r\n \r\n\r\nThe Company operates in one reportable segment, furniture products.&nbsp;&nbsp;... <a href=\"http://secfilings.nasdaq.com/edgar_conv_html%2f2019%2f09%2f13%2f0000897101-19-000829.html#FIS_BUSINESS\" target=\"_blank\">More</a> ...&nbsp;&nbsp;\r\n", "KeyExecutives": [{"name": "Derek P. Schmidt", "title": "Chief Operating & Financial Officer"}, {"name": "Jerald K. Dittmer", "title": "President, Chief Executive Officer & Director"}, {"name": "Michael J. Mcclaflin", "title": "Chief Information Officer"}], "Number_of_employees": ["NO INFO"], "Subsidiaries": ["NO INFO"]}