{"ModuleTitle": "Company Description", "CompanyName": "Verisk Analytics, Inc.", "Symbol": "VRSK", "Address": "545 WASHINGTON BOULEVARD, JERSEY CITY, New Jersey, 07310-1686, United States of America", "Phone": "201-469-2000", "Industry": "EDP Services", "Sector": "Technology", "Region": "North America", "CompanyDescription": "Verisk is a leading data analytics provider serving customers in insurance,\r\nenergy and specialized markets, and financial services. Using advanced\r\ntechnologies to collect and analyze billions of records, we draw on unique data\r\nassets and deep domain expertise to provide innovations that may be integrated\r\ninto customer workflows. We offer predictive analytics and decision support\r\nsolutions to customers in rating, underwriting, claims, catastrophe and weather\r\nrisk, natural resources intelligence, economic forecasting, commercial banking\r\nand finance, and many other fields. In the United States, or U.S., and around\r\nthe world, we help customers protect people, property, and financial assets.\r\nOur customers use our solutions to make better decisions about risk and\r\nopportunities with greater efficiency and discipline.&nbsp;&nbsp;... <a href=\"http://secfilings.nasdaq.com/edgar_conv_html%2f2020%2f02%2f18%2f0001442145-20-000012.html#FIS_BUSINESS\" target=\"_blank\">More</a> ...&nbsp;&nbsp;\r\n", "KeyExecutives": [{"name": "Lee M. Shavel", "title": "Chief Financial Officer & Executive Vice President"}, {"name": "Mark V. Anquillare", "title": "Chief Operating Officer & Executive Vice President"}, {"name": "Nicholas Daffan", "title": "Chief Information Officer & Executive VP"}, {"name": "Scott G. Stephenson", "title": "Chairman, President & Chief Executive Officer"}]}