[{"SharesOutstandingPCT": ["49.36 %"], "ShareoutstandingTotal": ["5"], "TotalHoldingsValue": ["$124"]}, {"ActivePositions": ["Increased Positions", "Decreased Positions", "Held Positions", "Total Institutional Shares", "New Positions", "Sold Out Positions"], "Holders": ["32", "29", "15", "76", "6", "10"], "Shares": ["142,827", "160,246", "2,155,068", "2,458,141", "38,392", "34,657"]}, {"OWNER_NAME": ["KEYBANK NATIONAL ASSOCIATION/OH", "DIMENSIONAL FUND ADVISORS LP", "ROYCE & ASSOCIATES LP", "BLACKROCK INC.", "HIGHTOWER ADVISORS, LLC"], "DATE": ["03/31/2020", "03/31/2020", "03/31/2020", "03/31/2020", "03/31/2020"], "SHARES_HELD": ["400,452", "353,996", "336,037", "189,002", "158,917"], "CHANGE(Shares)": ["0", "1,128", "-108,727", "974", "79"], "CHANGE(%)": ["0%", "0.32%", "-24.446%", "0.518%", "0.05%"], "MARKET_VALUE": ["$20,175", "$17,834", "$16,930", "$9,522", "$8,006"]}]