{"ModuleTitle": "Company Description", "CompanyName": "CECO Environmental Corp.", "Symbol": "CECE", "Address": "14651 NORTH DALLAS PARKWAY SUITE 500, DALLAS, Texas, 75254", "Phone": "(513) 458-2600", "Industry": "Pollution Control Equipment", "Sector": "Capital Goods", "Region": "North America", "CompanyDescription": "CECO Environmental Corp. (\"CECO\" or the \"Company\") is a global leader in\r\nindustrial air quality and fluid handling serving the energy, industrial and\r\nother niche markets through an attractive asset-light business model. CECO\r\nprovides innovative technology and application expertise that helps companies\r\ngrow their businesses with safe, clean, and more efficient solutions to help\r\nprotect our shared environment.\r\n\r\nCECO serves diverse industries globally by working to improve air quality,\r\noptimize the energy value chain, and provide customized engineered solutions in\r\nour customer's mission critical applications. The secular growth industries CECO\r\nserves include oil and gas, power generation, water and wastewater, battery\r\nproduction, poly silicon fabrication, chemical and petrochemical processing,\r\nalong with a wide range of other industries.&nbsp;&nbsp;... <a href=\"http://secfilings.nasdaq.com/edgar_conv_html%2f2020%2f03%2f04%2f0001564590-20-008551.html#FIS_BUSINESS\" target=\"_blank\">More</a> ...&nbsp;&nbsp;\r\n", "KeyExecutives": [{"name": "Dennis Robert Sadlowski", "title": "Chief Executive Officer & Director"}, {"name": "Martin Pranger", "title": "Chief Technology Officer"}, {"name": "Matthew Kurt Eckl", "title": "Chief Financial Officer"}], "Number_of_employees": ["NO INFO"], "Subsidiaries": ["NO INFO"]}